toucan/__init__.py
toucan/FaceCan/__init__.py
toucan/FaceCan/detection/__init__.py
toucan/FaceCan/detection/detection.py
toucan/models/__init__.py
toucan/models/models.py
the_toucan-1.1.9.dist-info/METADATA
the_toucan-1.1.9.dist-info/WHEEL
the_toucan-1.1.9.dist-info/top_level.txt
the_toucan-1.1.9.dist-info/RECORD
