Metadata-Version: 2.4
Name: the-toucan
Version: 1.1.9
Requires-Python: >=3.9
Requires-Dist: numpy
Requires-Dist: torch
Requires-Dist: torchvision
Requires-Dist: albumentations
Requires-Dist: Pillow
Dynamic: requires-dist
Dynamic: requires-python
